{
  "전산회계2급": {
    "전산회계2급": [
      {
        "exam": "제111회",
        "files": [
          {
            "name": "제111회-전산회계2급-A형.pdf",
            "type": "pdf",
            "path": "전산회계/전산회계2급/제111회-전산회계2급-A형.pdf"
          },
          {
            "name": "제111회-전산회계2급-B형.pdf",
            "type": "pdf",
            "path": "전산회계/전산회계2급/제111회-전산회계2급-B형.pdf"
          },
          {
            "name": "제111회-전산회계2급-확정답안.pdf",
            "type": "pdf",
            "path": "전산회계/전산회계2급/제111회-전산회계2급-확정답안.pdf"
          },
          {
            "name": "제111회-전산세무회계-수험용데이터.zip",
            "type": "zip",
            "path": "전산회계/전산회계2급/제111회-전산세무회계-수험용데이터.zip"
          }
        ]
      },
      {
        "exam": "제112회",
        "files": [
          {
            "name": "제112회-전산회계2급-A형.pdf",
            "type": "pdf",
            "path": "전산회계/전산회계2급/제112회-전산회계2급-A형.pdf"
          },
          {
            "name": "제112회-전산회계2급-B형.pdf",
            "type": "pdf",
            "path": "전산회계/전산회계2급/제112회-전산회계2급-B형.pdf"
          },
          {
            "name": "제112회-전산회계2급-확정답안.pdf",
            "type": "pdf",
            "path": "전산회계/전산회계2급/제112회-전산회계2급-확정답안.pdf"
          },
          {
            "name": "제112회-전산세무회계-수험용데이터-1.zip",
            "type": "zip",
            "path": "전산회계/전산회계2급/제112회-전산세무회계-수험용데이터-1.zip"
          }
        ]
      },
      {
        "exam": "제114회",
        "files": [
          {
            "name": "제114회-전산회계2급-A형.pdf",
            "type": "pdf",
            "path": "전산회계/전산회계2급/제114회-전산회계2급-A형.pdf"
          },
          {
            "name": "제114회-전산회계2급-B형.pdf",
            "type": "pdf",
            "path": "전산회계/전산회계2급/제114회-전산회계2급-B형.pdf"
          },
          {
            "name": "제114회-전산회계2급-확정답안.pdf",
            "type": "pdf",
            "path": "전산회계/전산회계2급/제114회-전산회계2급-확정답안.pdf"
          },
          {
            "name": "제114회-전산세무회계-수험용데이터-1.zip",
            "type": "zip",
            "path": "전산회계/전산회계2급/제114회-전산세무회계-수험용데이터-1.zip"
          }
        ]
      },
      {
        "exam": "제115회",
        "files": [
          {
            "name": "제115회-전산회계2급-A형.pdf",
            "type": "pdf",
            "path": "전산회계/전산회계2급/제115회-전산회계2급-A형.pdf"
          },
          {
            "name": "제115회-전산회계2급-B형.pdf",
            "type": "pdf",
            "path": "전산회계/전산회계2급/제115회-전산회계2급-B형.pdf"
          },
          {
            "name": "제115회-전산회계2급-확정답안.pdf",
            "type": "pdf",
            "path": "전산회계/전산회계2급/제115회-전산회계2급-확정답안.pdf"
          },
          {
            "name": "제115회-전산세무회계-수험용데이터.zip",
            "type": "zip",
            "path": "전산회계/전산회계2급/제115회-전산세무회계-수험용데이터.zip"
          }
        ]
      },
      {
        "exam": "제116회",
        "files": [
          {
            "name": "제116회-전산회계2급-A형.pdf",
            "type": "pdf",
            "path": "전산회계/전산회계2급/제116회-전산회계2급-A형.pdf"
          },
          {
            "name": "제116회-전산회계2급-B형.pdf",
            "type": "pdf",
            "path": "전산회계/전산회계2급/제116회-전산회계2급-B형.pdf"
          },
          {
            "name": "제116회-전산회계2급-확정답안.pdf",
            "type": "pdf",
            "path": "전산회계/전산회계2급/제116회-전산회계2급-확정답안.pdf"
          },
          {
            "name": "제116회-전산세무회계-수험용데이터.zip",
            "type": "zip",
            "path": "전산회계/전산회계2급/제116회-전산세무회계-수험용데이터.zip"
          }
        ]
      },
      {
        "exam": "제117회",
        "files": [
          {
            "name": "제117회-전산회계2급-A형.pdf",
            "type": "pdf",
            "path": "전산회계/전산회계2급/제117회-전산회계2급-A형.pdf"
          },
          {
            "name": "제117회-전산회계2급-B형.pdf",
            "type": "pdf",
            "path": "전산회계/전산회계2급/제117회-전산회계2급-B형.pdf"
          },
          {
            "name": "제117회-전산회계2급-확정답안.pdf",
            "type": "pdf",
            "path": "전산회계/전산회계2급/제117회-전산회계2급-확정답안.pdf"
          },
          {
            "name": "제117회-전산세무회계-수험용데이터.zip",
            "type": "zip",
            "path": "전산회계/전산회계2급/제117회-전산세무회계-수험용데이터.zip"
          }
        ]
      },
      {
        "exam": "제118회",
        "files": [
          {
            "name": "제118회-전산회계2급-A형.pdf",
            "type": "pdf",
            "path": "전산회계/전산회계2급/제118회-전산회계2급-A형.pdf"
          },
          {
            "name": "제118회-전산회계2급-B형.pdf",
            "type": "pdf",
            "path": "전산회계/전산회계2급/제118회-전산회계2급-B형.pdf"
          },
          {
            "name": "제118회-전산회계2급-확정답안.pdf",
            "type": "pdf",
            "path": "전산회계/전산회계2급/제118회-전산회계2급-확정답안.pdf"
          },
          {
            "name": "제118회-전산세무회계-수험용데이터.zip",
            "type": "zip",
            "path": "전산회계/전산회계2급/제118회-전산세무회계-수험용데이터.zip"
          }
        ]
      },
      {
        "exam": "제119회",
        "files": [
          {
            "name": "제119회-전산회계2급-A형.pdf",
            "type": "pdf",
            "path": "전산회계/전산회계2급/제119회-전산회계2급-A형.pdf"
          },
          {
            "name": "제119회-전산회계2급-B형.pdf",
            "type": "pdf",
            "path": "전산회계/전산회계2급/제119회-전산회계2급-B형.pdf"
          },
          {
            "name": "제119회-전산회계2급-확정답안.pdf",
            "type": "pdf",
            "path": "전산회계/전산회계2급/제119회-전산회계2급-확정답안.pdf"
          },
          {
            "name": "제119회-전산세무회계-수험용데이터-3.zip",
            "type": "zip",
            "path": "전산회계/전산회계2급/제119회-전산세무회계-수험용데이터-3.zip"
          }
        ]
      },
      {
        "exam": "제120회",
        "files": [
          {
            "name": "제120회-전산회계2급-A형.pdf",
            "type": "pdf",
            "path": "전산회계/전산회계2급/제120회-전산회계2급-A형.pdf"
          },
          {
            "name": "제120회-전산회계2급-B형.pdf",
            "type": "pdf",
            "path": "전산회계/전산회계2급/제120회-전산회계2급-B형.pdf"
          },
          {
            "name": "제120회-전산회계2급-확정답안.pdf",
            "type": "pdf",
            "path": "전산회계/전산회계2급/제120회-전산회계2급-확정답안.pdf"
          },
          {
            "name": "제120회-전산회계2급.zip",
            "type": "zip",
            "path": "전산회계/전산회계2급/제120회-전산회계2급.zip"
          },
          {
            "name": "2025년-6월-수험용데이터.zip",
            "type": "zip",
            "path": "전산회계/전산회계2급/2025년-6월-수험용데이터.zip"
          }
        ]
      },
      {
        "exam": "제121회",
        "files": [
          {
            "name": "제121회-전산회계2급-A형.pdf",
            "type": "pdf",
            "path": "전산회계/전산회계2급/제121회-전산회계2급-A형.pdf"
          },
          {
            "name": "제121회-전산회계2급-B형.pdf",
            "type": "pdf",
            "path": "전산회계/전산회계2급/제121회-전산회계2급-B형.pdf"
          },
          {
            "name": "제121회-전산회계2급-확정답안.pdf",
            "type": "pdf",
            "path": "전산회계/전산회계2급/제121회-전산회계2급-확정답안.pdf"
          },
          {
            "name": "제121회-전산세무회계-수험용데이터-3.zip",
            "type": "zip",
            "path": "전산회계/전산회계2급/제121회-전산세무회계-수험용데이터-3.zip"
          }
        ]
      },
      {
        "exam": "제122회",
        "files": [
          {
            "name": "제122회-전산회계2급-A형-1.pdf",
            "type": "pdf",
            "path": "전산회계/전산회계2급/제122회-전산회계2급-A형-1.pdf"
          },
          {
            "name": "제122회-전산회계2급-B형-1.pdf",
            "type": "pdf",
            "path": "전산회계/전산회계2급/제122회-전산회계2급-B형-1.pdf"
          },
          {
            "name": "제122회-전산회계2급-확정답안-1.pdf",
            "type": "pdf",
            "path": "전산회계/전산회계2급/제122회-전산회계2급-확정답안-1.pdf"
          },
          {
            "name": "제122회-2025년-10월-수험용데이터-1.zip",
            "type": "zip",
            "path": "전산회계/전산회계2급/제122회-2025년-10월-수험용데이터-1.zip"
          }
        ]
      }
    ]
  },
  "전산세무1급": {
    "전산세무1급": [
      {
        "exam": "제112회",
        "files": [
          {
            "name": "제112회-전산세무1급-A형.pdf",
            "type": "pdf",
            "path": "전산회계/전산세무1급/제112회-전산세무1급-A형.pdf"
          },
          {
            "name": "제112회-전산세무1급-B형.pdf",
            "type": "pdf",
            "path": "전산회계/전산세무1급/제112회-전산세무1급-B형.pdf"
          },
          {
            "name": "제112회-전산세무1급-확정답안.pdf",
            "type": "pdf",
            "path": "전산회계/전산세무1급/제112회-전산세무1급-확정답안.pdf"
          },
          {
            "name": "제112회-전산세무회계-수험용데이터-4.zip",
            "type": "zip",
            "path": "전산회계/전산세무1급/제112회-전산세무회계-수험용데이터-4.zip"
          }
        ]
      },
      {
        "exam": "제113회",
        "files": [
          {
            "name": "제113회-전산세무1급-A형.pdf",
            "type": "pdf",
            "path": "전산회계/전산세무1급/제113회-전산세무1급-A형.pdf"
          },
          {
            "name": "제113회-전산세무1급-B형.pdf",
            "type": "pdf",
            "path": "전산회계/전산세무1급/제113회-전산세무1급-B형.pdf"
          },
          {
            "name": "제113회-전산세무1급-확정답안.pdf",
            "type": "pdf",
            "path": "전산회계/전산세무1급/제113회-전산세무1급-확정답안.pdf"
          },
          {
            "name": "제113회-전산세무회계-수험용데이터-3.zip",
            "type": "zip",
            "path": "전산회계/전산세무1급/제113회-전산세무회계-수험용데이터-3.zip"
          }
        ]
      },
      {
        "exam": "제114회",
        "files": [
          {
            "name": "제114회-전산세무1급-A형.pdf",
            "type": "pdf",
            "path": "전산회계/전산세무1급/제114회-전산세무1급-A형.pdf"
          },
          {
            "name": "제114회-전산세무1급-B형.pdf",
            "type": "pdf",
            "path": "전산회계/전산세무1급/제114회-전산세무1급-B형.pdf"
          },
          {
            "name": "제114회-전산세무1급-확정답안.pdf",
            "type": "pdf",
            "path": "전산회계/전산세무1급/제114회-전산세무1급-확정답안.pdf"
          },
          {
            "name": "제114회-전산세무회계-수험용데이터-4.zip",
            "type": "zip",
            "path": "전산회계/전산세무1급/제114회-전산세무회계-수험용데이터-4.zip"
          }
        ]
      },
      {
        "exam": "제115회",
        "files": [
          {
            "name": "제115회-전산세무1급-A형.pdf",
            "type": "pdf",
            "path": "전산회계/전산세무1급/제115회-전산세무1급-A형.pdf"
          },
          {
            "name": "제115회-전산세무1급-B형.pdf",
            "type": "pdf",
            "path": "전산회계/전산세무1급/제115회-전산세무1급-B형.pdf"
          },
          {
            "name": "제115회-전산세무1급-확정답안.pdf",
            "type": "pdf",
            "path": "전산회계/전산세무1급/제115회-전산세무1급-확정답안.pdf"
          },
          {
            "name": "제115회-전산세무회계-수험용데이터-3.zip",
            "type": "zip",
            "path": "전산회계/전산세무1급/제115회-전산세무회계-수험용데이터-3.zip"
          }
        ]
      },
      {
        "exam": "제116회",
        "files": [
          {
            "name": "제116회-전산세무1급-A형.pdf",
            "type": "pdf",
            "path": "전산회계/전산세무1급/제116회-전산세무1급-A형.pdf"
          },
          {
            "name": "제116회-전산세무1급-B형.pdf",
            "type": "pdf",
            "path": "전산회계/전산세무1급/제116회-전산세무1급-B형.pdf"
          },
          {
            "name": "제116회-전산세무1급-확정답안.pdf",
            "type": "pdf",
            "path": "전산회계/전산세무1급/제116회-전산세무1급-확정답안.pdf"
          },
          {
            "name": "제116회-전산세무회계-수험용데이터-3.zip",
            "type": "zip",
            "path": "전산회계/전산세무1급/제116회-전산세무회계-수험용데이터-3.zip"
          }
        ]
      },
      {
        "exam": "제117회",
        "files": [
          {
            "name": "제117회-전산세무1급-A형.pdf",
            "type": "pdf",
            "path": "전산회계/전산세무1급/제117회-전산세무1급-A형.pdf"
          },
          {
            "name": "제117회-전산세무1급-B형.pdf",
            "type": "pdf",
            "path": "전산회계/전산세무1급/제117회-전산세무1급-B형.pdf"
          },
          {
            "name": "제117회-전산세무1급-확정답안.pdf",
            "type": "pdf",
            "path": "전산회계/전산세무1급/제117회-전산세무1급-확정답안.pdf"
          },
          {
            "name": "제117회-전산세무회계-수험용데이터-3.zip",
            "type": "zip",
            "path": "전산회계/전산세무1급/제117회-전산세무회계-수험용데이터-3.zip"
          }
        ]
      },
      {
        "exam": "제118회",
        "files": [
          {
            "name": "제118회-전산세무1급-A형.pdf",
            "type": "pdf",
            "path": "전산회계/전산세무1급/제118회-전산세무1급-A형.pdf"
          },
          {
            "name": "제118회-전산세무1급-B형.pdf",
            "type": "pdf",
            "path": "전산회계/전산세무1급/제118회-전산세무1급-B형.pdf"
          },
          {
            "name": "제118회-전산세무1급-확정답안.pdf",
            "type": "pdf",
            "path": "전산회계/전산세무1급/제118회-전산세무1급-확정답안.pdf"
          },
          {
            "name": "제118회-전산세무회계-수험용데이터-3.zip",
            "type": "zip",
            "path": "전산회계/전산세무1급/제118회-전산세무회계-수험용데이터-3.zip"
          }
        ]
      },
      {
        "exam": "제119회",
        "files": [
          {
            "name": "제119회-전산세무1급-A형.pdf",
            "type": "pdf",
            "path": "전산회계/전산세무1급/제119회-전산세무1급-A형.pdf"
          },
          {
            "name": "제119회-전산세무1급-B형.pdf",
            "type": "pdf",
            "path": "전산회계/전산세무1급/제119회-전산세무1급-B형.pdf"
          },
          {
            "name": "제119회-전산세무1급-확정답안.pdf",
            "type": "pdf",
            "path": "전산회계/전산세무1급/제119회-전산세무1급-확정답안.pdf"
          },
          {
            "name": "제119회-전산세무회계-수험용데이터-3.zip",
            "type": "zip",
            "path": "전산회계/전산세무1급/제119회-전산세무회계-수험용데이터-3.zip"
          }
        ]
      },
      {
        "exam": "제120회",
        "files": [
          {
            "name": "제120회-전산세무1급-A형.pdf",
            "type": "pdf",
            "path": "전산회계/전산세무1급/제120회-전산세무1급-A형.pdf"
          },
          {
            "name": "제120회-전산세무1급-B형.pdf",
            "type": "pdf",
            "path": "전산회계/전산세무1급/제120회-전산세무1급-B형.pdf"
          },
          {
            "name": "제120회-전산세무1급-확정답안.pdf",
            "type": "pdf",
            "path": "전산회계/전산세무1급/제120회-전산세무1급-확정답안.pdf"
          },
          {
            "name": "제120회-전산세무1급.zip",
            "type": "zip",
            "path": "전산회계/전산세무1급/제120회-전산세무1급.zip"
          },
          {
            "name": "2025년-6월-수험용데이터-3.zip",
            "type": "zip",
            "path": "전산회계/전산세무1급/2025년-6월-수험용데이터-3.zip"
          }
        ]
      },
      {
        "exam": "제121회",
        "files": [
          {
            "name": "제121회-전산세무1급-A형.pdf",
            "type": "pdf",
            "path": "전산회계/전산세무1급/제121회-전산세무1급-A형.pdf"
          },
          {
            "name": "제121회-전산세무1급-B형.pdf",
            "type": "pdf",
            "path": "전산회계/전산세무1급/제121회-전산세무1급-B형.pdf"
          },
          {
            "name": "제121회-전산세무1급-확정답안.pdf",
            "type": "pdf",
            "path": "전산회계/전산세무1급/제121회-전산세무1급-확정답안.pdf"
          },
          {
            "name": "제121회-전산세무1급.zip",
            "type": "zip",
            "path": "전산회계/전산세무1급/제121회-전산세무1급.zip"
          },
          {
            "name": "제121회-전산세무회계-수험용데이터.zip",
            "type": "zip",
            "path": "전산회계/전산세무1급/제121회-전산세무회계-수험용데이터.zip"
          }
        ]
      },
      {
        "exam": "제122회",
        "files": [
          {
            "name": "제122회-전산세무1급-A형.pdf",
            "type": "pdf",
            "path": "전산회계/전산세무1급/제122회-전산세무1급-A형.pdf"
          },
          {
            "name": "제122회-전산세무1급-B형.pdf",
            "type": "pdf",
            "path": "전산회계/전산세무1급/제122회-전산세무1급-B형.pdf"
          },
          {
            "name": "제122회-전산세무1급-확정답안.pdf",
            "type": "pdf",
            "path": "전산회계/전산세무1급/제122회-전산세무1급-확정답안.pdf"
          },
          {
            "name": "제122회-2025년-10월-수험용데이터-3.zip",
            "type": "zip",
            "path": "전산회계/전산세무1급/제122회-2025년-10월-수험용데이터-3.zip"
          }
        ]
      }
    ]
  },
  "전산세무2급": {
    "전산세무2급": [
      {
        "exam": "제112회",
        "files": [
          {
            "name": "제112회-전산세무2급-A형.pdf",
            "type": "pdf",
            "path": "전산회계/전산세무2급/제112회-전산세무2급-A형.pdf"
          },
          {
            "name": "제112회-전산세무2급-B형.pdf",
            "type": "pdf",
            "path": "전산회계/전산세무2급/제112회-전산세무2급-B형.pdf"
          },
          {
            "name": "제112회-전산세무2급-확정답안.pdf",
            "type": "pdf",
            "path": "전산회계/전산세무2급/제112회-전산세무2급-확정답안.pdf"
          },
          {
            "name": "제112회-전산세무회계-수험용데이터-3.zip",
            "type": "zip",
            "path": "전산회계/전산세무2급/제112회-전산세무회계-수험용데이터-3.zip"
          }
        ]
      },
      {
        "exam": "제113회",
        "files": [
          {
            "name": "제113회-전산세무2급-A형.pdf",
            "type": "pdf",
            "path": "전산회계/전산세무2급/제113회-전산세무2급-A형.pdf"
          },
          {
            "name": "제113회-전산세무2급-B형.pdf",
            "type": "pdf",
            "path": "전산회계/전산세무2급/제113회-전산세무2급-B형.pdf"
          },
          {
            "name": "제113회-전산세무2급-확정답안.pdf",
            "type": "pdf",
            "path": "전산회계/전산세무2급/제113회-전산세무2급-확정답안.pdf"
          },
          {
            "name": "제113회-전산세무회계-수험용데이터-2.zip",
            "type": "zip",
            "path": "전산회계/전산세무2급/제113회-전산세무회계-수험용데이터-2.zip"
          }
        ]
      },
      {
        "exam": "제114회",
        "files": [
          {
            "name": "제114회-전산세무2급-A형.pdf",
            "type": "pdf",
            "path": "전산회계/전산세무2급/제114회-전산세무2급-A형.pdf"
          },
          {
            "name": "제114회-전산세무2급-B형.pdf",
            "type": "pdf",
            "path": "전산회계/전산세무2급/제114회-전산세무2급-B형.pdf"
          },
          {
            "name": "제114회-전산세무2급-확정답안.pdf",
            "type": "pdf",
            "path": "전산회계/전산세무2급/제114회-전산세무2급-확정답안.pdf"
          },
          {
            "name": "제114회-전산세무회계-수험용데이터-3.zip",
            "type": "zip",
            "path": "전산회계/전산세무2급/제114회-전산세무회계-수험용데이터-3.zip"
          }
        ]
      },
      {
        "exam": "제115회",
        "files": [
          {
            "name": "제115회-전산세무2급-A형.pdf",
            "type": "pdf",
            "path": "전산회계/전산세무2급/제115회-전산세무2급-A형.pdf"
          },
          {
            "name": "제115회-전산세무2급-B형.pdf",
            "type": "pdf",
            "path": "전산회계/전산세무2급/제115회-전산세무2급-B형.pdf"
          },
          {
            "name": "제115회-전산세무2급-확정답안.pdf",
            "type": "pdf",
            "path": "전산회계/전산세무2급/제115회-전산세무2급-확정답안.pdf"
          },
          {
            "name": "제115회-전산세무회계-수험용데이터-2.zip",
            "type": "zip",
            "path": "전산회계/전산세무2급/제115회-전산세무회계-수험용데이터-2.zip"
          }
        ]
      },
      {
        "exam": "제116회",
        "files": [
          {
            "name": "제116회-전산세무2급-A형.pdf",
            "type": "pdf",
            "path": "전산회계/전산세무2급/제116회-전산세무2급-A형.pdf"
          },
          {
            "name": "제116회-전산세무2급-B형.pdf",
            "type": "pdf",
            "path": "전산회계/전산세무2급/제116회-전산세무2급-B형.pdf"
          },
          {
            "name": "제116회-전산세무2급-확정답안.pdf",
            "type": "pdf",
            "path": "전산회계/전산세무2급/제116회-전산세무2급-확정답안.pdf"
          },
          {
            "name": "제116회-전산세무회계-수험용데이터-2.zip",
            "type": "zip",
            "path": "전산회계/전산세무2급/제116회-전산세무회계-수험용데이터-2.zip"
          }
        ]
      },
      {
        "exam": "제117회",
        "files": [
          {
            "name": "제117회-전산세무2급-A형-2.pdf",
            "type": "pdf",
            "path": "전산회계/전산세무2급/제117회-전산세무2급-A형-2.pdf"
          },
          {
            "name": "제117회-전산세무2급-B형-2.pdf",
            "type": "pdf",
            "path": "전산회계/전산세무2급/제117회-전산세무2급-B형-2.pdf"
          },
          {
            "name": "제117회-전산세무2급-확정답안-2.pdf",
            "type": "pdf",
            "path": "전산회계/전산세무2급/제117회-전산세무2급-확정답안-2.pdf"
          },
          {
            "name": "제117회-전산세무회계-수험용데이터-2.zip",
            "type": "zip",
            "path": "전산회계/전산세무2급/제117회-전산세무회계-수험용데이터-2.zip"
          }
        ]
      },
      {
        "exam": "제118회",
        "files": [
          {
            "name": "제118회-전산세무2급-A형.pdf",
            "type": "pdf",
            "path": "전산회계/전산세무2급/제118회-전산세무2급-A형.pdf"
          },
          {
            "name": "제118회-전산세무2급-B형.pdf",
            "type": "pdf",
            "path": "전산회계/전산세무2급/제118회-전산세무2급-B형.pdf"
          },
          {
            "name": "제118회-전산세무2급-확정답안.pdf",
            "type": "pdf",
            "path": "전산회계/전산세무2급/제118회-전산세무2급-확정답안.pdf"
          },
          {
            "name": "제118회-전산세무회계-수험용데이터-2.zip",
            "type": "zip",
            "path": "전산회계/전산세무2급/제118회-전산세무회계-수험용데이터-2.zip"
          }
        ]
      },
      {
        "exam": "제119회",
        "files": [
          {
            "name": "제119회-전산세무2급-A형.pdf",
            "type": "pdf",
            "path": "전산회계/전산세무2급/제119회-전산세무2급-A형.pdf"
          },
          {
            "name": "제119회-전산세무2급-B형.pdf",
            "type": "pdf",
            "path": "전산회계/전산세무2급/제119회-전산세무2급-B형.pdf"
          },
          {
            "name": "제119회-전산세무2급-확정답안.pdf",
            "type": "pdf",
            "path": "전산회계/전산세무2급/제119회-전산세무2급-확정답안.pdf"
          },
          {
            "name": "제119회-전산세무회계-수험용데이터-3.zip",
            "type": "zip",
            "path": "전산회계/전산세무2급/제119회-전산세무회계-수험용데이터-3.zip"
          }
        ]
      },
      {
        "exam": "제120회",
        "files": [
          {
            "name": "제120회-전산세무2급-A형.pdf",
            "type": "pdf",
            "path": "전산회계/전산세무2급/제120회-전산세무2급-A형.pdf"
          },
          {
            "name": "제120회-전산세무2급-B형.pdf",
            "type": "pdf",
            "path": "전산회계/전산세무2급/제120회-전산세무2급-B형.pdf"
          },
          {
            "name": "제120회-전산세무2급-확정답안.pdf",
            "type": "pdf",
            "path": "전산회계/전산세무2급/제120회-전산세무2급-확정답안.pdf"
          },
          {
            "name": "제120회-전산세무회계-수험용데이터-2.zip",
            "type": "zip",
            "path": "전산회계/전산세무2급/제120회-전산세무회계-수험용데이터-2.zip"
          }
        ]
      },
      {
        "exam": "제121회",
        "files": [
          {
            "name": "제121회-전산세무2급-A형.pdf",
            "type": "pdf",
            "path": "전산회계/전산세무2급/제121회-전산세무2급-A형.pdf"
          },
          {
            "name": "제121회-전산세무2급-B형.pdf",
            "type": "pdf",
            "path": "전산회계/전산세무2급/제121회-전산세무2급-B형.pdf"
          },
          {
            "name": "제121회-전산세무2급-확정답안.pdf",
            "type": "pdf",
            "path": "전산회계/전산세무2급/제121회-전산세무2급-확정답안.pdf"
          },
          {
            "name": "제121회-전산세무회계-수험용데이터-1.zip",
            "type": "zip",
            "path": "전산회계/전산세무2급/제121회-전산세무회계-수험용데이터-1.zip"
          }
        ]
      },
      {
        "exam": "제122회",
        "files": [
          {
            "name": "제122회-전산세무2급-A형.pdf",
            "type": "pdf",
            "path": "전산회계/전산세무2급/제122회-전산세무2급-A형.pdf"
          },
          {
            "name": "제122회-전산세무2급-B형.pdf",
            "type": "pdf",
            "path": "전산회계/전산세무2급/제122회-전산세무2급-B형.pdf"
          },
          {
            "name": "제122회-전산세무2급-확정답안.pdf",
            "type": "pdf",
            "path": "전산회계/전산세무2급/제122회-전산세무2급-확정답안.pdf"
          },
          {
            "name": "제122회-2025년-10월-수험용데이터-2.zip",
            "type": "zip",
            "path": "전산회계/전산세무2급/제122회-2025년-10월-수험용데이터-2.zip"
          }
        ]
      }
    ]
  }
}

